{
  "smoke": {
    "description": "Fast FUSE viability checks with small deterministic workloads.",
    "modules": [
      "ported.juicefs.random_rw",
      "drive9.workflow.git_fast_clone",
      "drive9.workflow.pack_unpack_cli"
    ],
    "strict_prereqs": false,
    "report_daily": false
  },
  "standard": {
    "description": "Mainline FUSE regression coverage for compatibility and Drive9 workflows.",
    "modules": [
      "community.pjdfstest",
      "community.fsx",
      "community.lock",
      "community.pyxattr",
      "ported.juicefs.fsrand",
      "ported.juicefs.random_stress",
      "ported.juicefs.cache_consistency",
      "ported.juicefs.rmr",
      "ported.juicefs.random_rw",
      "git.official.functional",
      "drive9.workflow.git_fast_clone",
      "drive9.workflow.git_blobless",
      "drive9.workflow.git_worktree",
      "drive9.workflow.auto_pack_profile",
      "drive9.workflow.auto_pack_umount_path",
      "drive9.workflow.portable_pack",
      "drive9.workflow.pack_unpack_cli",
      "drive9.workflow.pack_git_clone"
    ],
    "strict_prereqs": true,
    "report_daily": false
  },
  "daily": {
    "description": "Daily stability, POSIX compatibility, Git compatibility, and performance run.",
    "modules": [
      "community.pjdfstest",
      "community.ltp.fs",
      "community.ltp.syscalls",
      "community.fio",
      "community.mdtest",
      "community.vdbench",
      "community.pyxattr",
      "community.fsx",
      "community.lock",
      "ported.juicefs.fsrand",
      "ported.juicefs.random_stress",
      "ported.juicefs.cache_consistency",
      "ported.juicefs.rmr",
      "ported.juicefs.random_rw",
      "git.official.functional",
      "git.official.perf",
      "drive9.workflow.git_fast_clone",
      "drive9.workflow.git_blobless",
      "drive9.workflow.git_worktree",
      "drive9.workflow.auto_pack_profile",
      "drive9.workflow.auto_pack_umount_path",
      "drive9.workflow.portable_pack",
      "drive9.workflow.pack_unpack_cli",
      "drive9.workflow.pack_git_clone",
      "drive9.workflow.perf"
    ],
    "strict_prereqs": true,
    "report_daily": true
  }
}
